{
  "frontend": {},
  "backend" : {},
  "globals": {
    "version": {
      "displayName": "Application version",
      "type": "string",
      "required": false,
      "example": "1.2.3"
    },
    "favicon": {
      "displayName": "Favicon",
      "type": "string",
      "required": false,
      "pattern": "^@[^:]+:(?:\\/?[\\w\\-\\d]+)+\\.(ico|png)$",
      "default": "@deep-root-angular:img/favicon.ico",
      "example": "@deep-root-angular:img/favicon.ico"
    },
    "basePath": {
      "displayName": "Application base path",
      "type": "string",
      "required": true,
      "example": "/",
      "default": "/"
    },
    "pageLoader|src": {
      "displayName": "Page loader source",
      "type": "string",
      "required": false,
      "pattern": "^@[^:]+:(?:\\/?[\\w\\-\\d]+)+\\.(png|jpg|gif)$",
      "default": "@deep-root-angular:img/loader.gif",
      "example": "@deep-root-angular:img/loader.gif"
    },
    "pageLoader|alt": {
      "displayName": "Page loader alternate text",
      "type": "string",
      "required": false,
      "default": "Loading...",
      "example": "Loading..."
    },
    "gtmContainerId": {
      "displayName": "Google Tag Manager (GTM) domain identifier",
      "type": "string",
      "required": false,
      "pattern": "^GTM\\-[a-zA-Z0-9]+$",
      "example": "GTM-XXXX"
    },
    "search|enabled": {
      "displayName": "Enable Search cluster?",
      "type": "boolean",
      "required": false,
      "example": false
    },
    "search|es|version": {
      "displayName": "ElasticSearch cluster version (1.5, 2.3, 5.1)",
      "type": "string",
      "required": false,
      "pattern": "^(5\\.1|2\\.3|1\\.5)$",
      "example": "2.3"
    },
    "logDrivers|sentry|dsn": {
      "displayName": "Sentry DSN",
      "type": "string",
      "required": false,
      "pattern": "^https?:\\/\\/[^:]+(:[^@]+)?@(app\\.getsentry\\.com|sentry\\.io)\\/[0-9]+$",
      "example": "https://72kshdbrgkebghkrb34iu5yb3ub:23l5hbk2v2jhg52uygvygvhmgv@app.getsentry.com/45747"
    },
    "serviceWorker|cache|enabled": {
      "displayName": "Enable Service Worker html caching?",
      "type": "boolean",
      "required": false,
      "example": false
    },
    "api|cache|enabled": {
      "displayName": "Enable API caching?",
      "type": "boolean",
      "required": false,
      "example": false
    },
    "api|cache|clusterSize": {
      "displayName": "API cache cluster size ('0.5', '1.6', '6.1', '13.5', '28.4', '58.2', '118', '237') GB",
      "type": "string",
      "required": false,
      "example": "0.5"
    },
    "api|cloudWatch|logging|enabled": {
      "displayName": "Enable CloudWatch logs for API Gateway?",
      "type": "boolean",
      "required": false,
      "example": false
    },
    "api|cloudWatch|logging|logLevel": {
      "displayName": "API Gateway CloudWatch log level ('OFF', 'INFO', 'ERROR')?",
      "type": "string",
      "required": false,
      "example": "INFO"
    },
    "api|cloudWatch|logging|dataTrace": {
      "displayName": "Log full requests/responses data for API Gateway?",
      "type": "boolean",
      "required": false,
      "example": false
    },
    "api|cloudWatch|metrics": {
      "displayName": "Enable CloudWatch metrics for API Gateway?",
      "type": "boolean",
      "required": false,
      "example": false
    },
    "api|authorizer|authorizerUri": {
      "displayName": "Authorizer Uniform Resource Identifier. For TOKEN type deep resource should be specified.",
      "type": "string",
      "required": false,
      "example": "@deep-account:authorizer:authorize"
    },
    "api|authorizer|type": {
      "displayName": "Authorizer type (TOKEN | COGNITO_USER_POOLS)",
      "type": "string",
      "required": false,
      "example": "TOKEN"
    },
    "api|authorizer|identitySource": {
      "displayName": "The source of the identity in an incoming request",
      "type": "string",
      "required": false,
      "example": "method.request.header.<headerName>"
    },
    "api|authorizer|authorizerResultTtlInSeconds": {
      "displayName": "The TTL of cached authorizer results",
      "type": "number",
      "required": false,
      "example": 300
    },
    "api|plan|quota|limit": {
      "displayName": "The maximum number of requests that can be made in a given time period.",
      "type": "number",
      "required": false,
      "example": 10000
    },
    "api|plan|quota|offset": {
      "displayName": "The number of requests subtracted from the given limit in the initial time period.",
      "type": "number",
      "required": false,
      "example": 0
    },
    "api|plan|quota|period": {
      "displayName": "The time period in which the limit applies. Valid values are 'DAY | WEEK | MONTH'.",
      "type": "string",
      "pattern": "^(DAY|WEEK|MONTH)$",
      "required": false,
      "example": "DAY"
    },
    "api|plan|throttle|burstLimit": {
      "displayName": "The API request burst limit, the maximum rate limit over a time ranging from one to a few seconds.",
      "type": "number",
      "required": false,
      "example": 200
    },
    "api|plan|throttle|rateLimit": {
      "displayName": "The API request steady-state rate limit.",
      "type": "number",
      "required": false,
      "example": 100
    }
  }
}
